pygments_style_dracula/__init__.py
pygments_style_dracula/dracula.py
pygments_style_dracula-1.2.5.1.dist-info/LICENSE
pygments_style_dracula-1.2.5.1.dist-info/METADATA
pygments_style_dracula-1.2.5.1.dist-info/WHEEL
pygments_style_dracula-1.2.5.1.dist-info/entry_points.txt
pygments_style_dracula-1.2.5.1.dist-info/top_level.txt
pygments_style_dracula-1.2.5.1.dist-info/RECORD
